RDG_networks/Classes.py
RDG_networks/__init__.py
RDG_networks/draw_segments.py
RDG_networks/generate_line_network.py
RDG_networks/generate_line_segments.py
RDG_networks/generate_line_segments_dynamic.py
RDG_networks/generate_line_segments_static.py
RDG_networks/get_intersection_segments.py
RDG_networks/sample_in_polygon.py
RDG_networks/save_data.py
RDG_networks/thickness/Classes.py
RDG_networks/thickness/__init__.py
RDG_networks/thickness/generate_line_segments_thickness.py
RDG_networks/thickness/generate_line_segments_thickness_static.py
RDG_networks/thickness/orientate_network.py
RDG_networks/thickness/sample_in_polygon.py
RDG_Networks-0.3.14.dist-info/LICENSE.txt
RDG_Networks-0.3.14.dist-info/METADATA
RDG_Networks-0.3.14.dist-info/WHEEL
RDG_Networks-0.3.14.dist-info/entry_points.txt
RDG_Networks-0.3.14.dist-info/top_level.txt
RDG_Networks-0.3.14.dist-info/RECORD
