Metadata-Version: 2.1
Name: RDG-Networks
Version: 0.3.14
Summary: RDG Networks project
Home-page: https://github.com/NiekMooij/RDG_networks
Author: Niek Mooij
Author-email: mooij.niek@gmail.com
License: All Rights Reserved
Classifier: Programming Language :: Python :: 3
Classifier: Operating System :: OS Independent
License-File: LICENSE.txt
Requires-Dist: networkx
Requires-Dist: numpy
Requires-Dist: scipy
Requires-Dist: shapely
Requires-Dist: typing
